coastlib/__init__.py
coastlib/bin/Fourier.exe
coastlib/data/__init__.py
coastlib/data/noaa_coops.py
coastlib/data/noaa_ncei.py
coastlib/data/wavewatch.py
coastlib/helper/__init__.py
coastlib/helper/environment.py
coastlib/helper/progress_bar.py
coastlib/math/__init__.py
coastlib/math/derivatives.py
coastlib/plotting/__init__.py
coastlib/plotting/rose.py
coastlib/plotting/styles.py
coastlib/stats/__init__.py
coastlib/stats/distributions.py
coastlib/stats/extreme.py
coastlib/stats/helper.py
coastlib/waves/LeMehaute.png
coastlib/waves/__init__.py
coastlib/waves/fenton.py
coastlib/waves/support.py
coastlib-1.0.0.dist-info/LICENSE.txt
coastlib-1.0.0.dist-info/METADATA
coastlib-1.0.0.dist-info/WHEEL
coastlib-1.0.0.dist-info/top_level.txt
coastlib-1.0.0.dist-info/RECORD
