Metadata-Version: 2.1
Name: coastlib
Version: 1.0.0
Summary: Coastal engineering library and tools
Home-page: https://github.com/georgebv/coastlib
Author: Georgii Bocharov
Author-email: bocharovgeorgii@gmail.com
License: GPLv3
Keywords: coastal ocean marine engineering
Platform: UNKNOWN
Classifier: Programming Language :: Python :: 3.7
Classifier: Development Status :: 4 - Beta
Classifier: Intended Audience :: Science/Research
Classifier: Topic :: Scientific/Engineering
Classifier: License :: OSI Approved :: GNU General Public License v3 (GPLv3)
